odoo/addons/account_move_chatter/README.rst
odoo/addons/account_move_chatter/__init__.py
odoo/addons/account_move_chatter/__manifest__.py
odoo/addons/account_move_chatter/i18n/account_move_chatter.pot
odoo/addons/account_move_chatter/i18n/da.po
odoo/addons/account_move_chatter/i18n/es.po
odoo/addons/account_move_chatter/i18n/fr.po
odoo/addons/account_move_chatter/i18n/pt.po
odoo/addons/account_move_chatter/models/__init__.py
odoo/addons/account_move_chatter/models/account_move.py
odoo/addons/account_move_chatter/readme/CONFIGURE.rst
odoo/addons/account_move_chatter/readme/CONTRIBUTORS.rst
odoo/addons/account_move_chatter/readme/DESCRIPTION.rst
odoo/addons/account_move_chatter/readme/USAGE.rst
odoo/addons/account_move_chatter/static/description/icon.png
odoo/addons/account_move_chatter/static/description/index.html
odoo/addons/account_move_chatter/views/account_move_views.xml
odoo12_addon_account_move_chatter-12.0.1.0.0.99.dev11.dist-info/METADATA
odoo12_addon_account_move_chatter-12.0.1.0.0.99.dev11.dist-info/WHEEL
odoo12_addon_account_move_chatter-12.0.1.0.0.99.dev11.dist-info/top_level.txt
odoo12_addon_account_move_chatter-12.0.1.0.0.99.dev11.dist-info/RECORD
